{
        "epcot-anthem": {
            "name": "EPCOT Anthem",
            "wled_preset": null,
            "music": "EPCOT_Anthem.wav",
            "actions": [
                {
                    "type": "url",
                    "url": "http://spaceshipearth.local/win&PL=39",
                    "method": "GET",
                    "delay": 0
                },
                {
                    "type": "url",
                    "url": "http://ssexl.local/win&PL=53",
                    "method": "GET",
                    "delay": 0
                }
            ],
            "wait_delay": 191
        },
        "epcot-40th": {
            "name": "EPCOT 40th Anniversary",
            "wled_preset": 26,
            "music": "EPCOT_Anniversary.wav",
            "actions": [
                {
                    "type": "url",
                    "url": "http://spaceshipearth.local/win&PL=14",
                    "method": "GET",
                    "delay": 0
                },
                {
                    "type": "url",
                    "url": "http://ssexl.local/win&PL=6",
                    "method": "GET",
                    "delay": 0
                }
            ],
            "wait_delay": 249
        },
        "HappilyEverAfter": {
            "name": "Happily Ever After",
            "wled_preset": null,
            "music": "HappilyEverAfter.mp3",
            "actions": [
                {
                    "type": "url",
                    "url": "http://spaceshipearth.local/win&PL=75",
                    "method": "GET",
                    "delay": 0
                }
            ],
            "wait_delay": 1363
        },
        "unknown-band": {
            "name": "Unknown Band",
            "wled_preset": null,
            "music": null,
            "actions": [
                {
                    "type": "brightsign",
                    "address": "192.168.1.91",
                    "port": 5000,
                    "command": "ShowStop"
                }
            ],
            "wait_delay": 2
        }
}